{
  "dependencies": {
    "apis1": {
      "resourceId": "/subscriptions/[parameters('subscriptionId')]/resourceGroups/[parameters('resourceGroupName')]/providers/Microsoft.ApiManagement/service/ArishProjectapi/apis/ArishProject",
      "type": "apis.azure"
    },
    "mssql1": {
      "secretStore": "AzureAppSettings",
      "resourceId": "/subscriptions/[parameters('subscriptionId')]/resourceGroups/[parameters('resourceGroupName')]/providers/Microsoft.Sql/servers/firstazuredatabaseserver/databases/firstAzureDatabase",
      "type": "mssql.azure",
      "connectionId": "ConnectionStrings:ArishDatabase",
      "dynamicId": null
    }
  }
}